simplenote_local/__init__.py
simplenote_local/cli.py
simplenote_local/version.py
simplenote_local-1.0.4.dist-info/licenses/LICENSE
simplenote_local-1.0.4.dist-info/METADATA
simplenote_local-1.0.4.dist-info/WHEEL
simplenote_local-1.0.4.dist-info/entry_points.txt
simplenote_local-1.0.4.dist-info/top_level.txt
simplenote_local-1.0.4.dist-info/RECORD
