Metadata-Version: 2.4
Name: simplenote_local
Version: 1.0.4
Summary: Sync notes to/from simplenote.com
Home-page: https://github.com/norm/simplenote-local
Author: Mark Norman Francis
Author-email: norm@201created.com
License: MIT
Classifier: License :: OSI Approved :: MIT License
Requires-Python: >=3.8
License-File: LICENSE
Requires-Dist: beautifulsoup4
Requires-Dist: markdownify
Requires-Dist: simple-colors
Requires-Dist: simplenote
Requires-Dist: toml
Requires-Dist: watchdog
Dynamic: author
Dynamic: author-email
Dynamic: classifier
Dynamic: description
Dynamic: description-content-type
Dynamic: home-page
Dynamic: license
Dynamic: license-file
Dynamic: requires-dist
Dynamic: requires-python
Dynamic: summary
